wool/locking/__init__.py
wool/locking/_cli.py
wool/locking/_lock.py
wool/locking/_pool.py
wool/locking/_session.py
wool/locking/_worker.py
wool_locking-0.1rc8.dist-info/METADATA
wool_locking-0.1rc8.dist-info/WHEEL
wool_locking-0.1rc8.dist-info/entry_points.txt
wool_locking-0.1rc8.dist-info/RECORD
