Metadata-Version: 2.4
Name: wool-locking
Version: 0.1rc8
Summary: A Wool plugin for distributed locking.
Author-email: Conrad Bzura <conrad@wool.io>
Maintainer-email: maintainers@wool.io
License:                                  Apache License
Classifier: Intended Audience :: Developers
Requires-Python: >=3.10
Requires-Dist: click
Requires-Dist: wool==0.1rc8
Provides-Extra: dev
Requires-Dist: pytest; extra == 'dev'
Requires-Dist: ruff; extra == 'dev'
